<?xml version="1.0" encoding="windows-1251"?>
<document>
  <ID>
    1291
  </ID>
  <link>
http://focused.ru/articles/bridge/comment-page-1#comment-40842
  </link>
  <date>
    2010-03-23T15:35:14Z
  </date>
  <query>
    Canon EOS 1000D body
  </query>
  <text>
    Странный достаточно ход … 1. Размер не так и мал. положить в
карман не получится, а значит сумочка обеспечена. Почему бы тогда
не взять зеркалку даже начального уровня? 2. Стоимость того же
samsung nx10 &gt; 20 000руб. Для мыльницы много. (SONY DSLR-A230L
(kit 18-55) – 16 000, CANON EOS 1000D body и NIKON D3000 kit AF-S
18-55 II – 18 000). 3. Как я понимаю, разброс объективов тоже не
сильно большой для таких моделей? Да и нужна эта полумера? Кому-то
хватает и простого маленького фотоаппарата, кому-то уже интереснее
зеркало купить … Это как купить маленький КАМАЗик (в природе не
существует) – и за хлебом ехать дороговато по топливу и неудобно в
городе, и груз возить маловат по сравнению с обычным …
  </text>
  <score-2>
    1
  </score-2>
  <score-3>
    2
  </score-3>
  <score-5>
    3
  </score-5>
  <type main="-">
    --
  </type>
  <real_object>
    --
  </real_object>
</document>
