<?xml version="1.0" encoding="windows-1251"?>
<document>
  <ID>
    14897
  </ID>
  <link>
    http://pure-sun.livejournal.com/3913.html
  </link>
  <date>
    2010-12-21T16:02:27Z
  </date>
  <query>
    Девушка с татуировкой дракона
  </query>
  <text>
    Только что дочитала творение Стига Ларсена &quot; Девушка с
татуировкой дракона &quot; (или M ? n som hatar kvinnor — «
Мужчины, которые ненавидят женщин » ). Я нахожусь под впечатлением.
Несомненно, моей любимицей стала девушка с тату дракона - Лисбет.
Не ожидала я, что &quot; увижу &quot; такую девушку в этой книге.
Она анорексичная социопатка, с тёмным прошлым, не умеет показывать
свои чувства, так как строила толстенную стену вокруг себя много
много лет. Необыкновенная девушка с кривой улыбкой. У неё
собственные представления о справедливости, своё мнение по поводу
всего и непоколебимые принципы. Она герой. Книга очень интересная,
заставляет читателя сопереживать, удивляться, волноваться и иногда
даже бросает в дрожь.Теперь входит в топ моих любимых книг и я уже
жду не дождусь, когда выйдет экранизация &quot; Девушки с
татуировкой дракона &quot; режиссёра Д.Финчера. Пока посмотрю, что
там шведы наснимали, а завтра в магазин за оставшимися частями
трилогии. :)
  </text>
  <score-2>
    2
  </score-2>
  <score-3>
    3
  </score-3>
  <score-5>
    5
  </score-5>
  <type main="+">
    B
  </type>
  <real_object>
    Девушка с татуировкой дракона
  </real_object>
</document>
