<?xml version="1.0" encoding="windows-1251"?>
<document>
  <ID>
    14012
  </ID>
  <link>
    http://anst-ana.livejournal.com/10263.html
  </link>
  <date>
    2010-03-04T15:48:43Z
  </date>
  <query>
    Харуки Мураками
  </query>
  <text>
    &quot; Вот зачем я это узнал? &quot; (Е. Гришковец) Стоя у
книжного прилавка на Выборгском вокзале, выбирала себе чтиво в
дорогу. Внимание привлекла книга &quot; Норвежский лес &quot;
Харуки Мураками. Вспомнилось, что преподаватель современной
литературы восторженно отзывалась о творчестве этого писателя и
настоятельно рекомендовала с ним ознакомиться. Честно прочитала
книгу до конца, но только зря потратила время. Редкостная
бессмыслица! Описываются страдания главного героя, но я до сих пор
не могу понять, отчего же он страдает? По замыслу автора, от
запутанных взаимоотношений с душевнобольной девушкой. Однако
глубоких чуЙств я там не нашла, как ни старалась. Причем не только
между главными героями. Много размышлений о сексе, смерти и
абсолютная нравственная инфантильность всех персонажей. Может, я
чего-то снова не понимаю? Поделитесь, други, размышлизмами!
  </text>
  <score-2>
    1
  </score-2>
  <score-3>
    1
  </score-3>
  <score-5>
    1
  </score-5>
  <type main="+">
    B
  </type>
  <real_object>
    Норвежский лес
  </real_object>
</document>
