<?xml version="1.0" encoding="windows-1251"?>
<document>
  <ID>
    14124
  </ID>
  <link>
    http://www.diary.ru/~Just3/p103260602.htm
  </link>
  <date>
    2010-04-04T08:51:56Z
  </date>
  <query>
    Харуки Мураками
  </query>
  <text>
    Книга буквально на днях вышла в Москве, я как фанат Мураками
не могла не удержаться, что бы не купить... &quot; Радио Мураками
&quot; - это сборник колонок, написанных им для модного японского
женского журнала &quot; Ан-ан &quot; . Иллюстрации к колонкам
сделаны Аюми Охаси по просьбе автора. Когда то я пыталась читать
его рассказы и осталась не в восторге. Поэтому я с некоторой
опаской открыла эту книгу и сразу прониклась. Его мысли, причем
человеческие мысли (а не заумные о мире во всем мире и т.д.), те
которые обычно кажутся нам странными. Он пишет о том, как тяжело
наверно быть лифчиком и какие весы ему нравятся, о музыке,
ресторанах и новомодном кино. И все это простыми, понятными
мыслями. Читая эту книгу, создается впечатление, что сидишь на
кухне с подругой, обсуждаешь какую-то тему, но вы постоянно
отступаете от нее и &quot; говорите нечто странное, но понятное вам
обеим &quot; . Он пишет свои мысли, говоря &quot; наверно вам
покажется это странным &quot; или &quot; наверно вы никогда не
думали об этом &quot; , а ты читаешь и думаешь &quot; думал, но
считал это странным &quot; (и делился такими мыслями только с той
самой близкой подругой)
  </text>
  <score-2>
    2
  </score-2>
  <score-3>
    3
  </score-3>
  <score-5>
    4
  </score-5>
  <type main="+">
    B
  </type>
  <real_object>
    Радио Мураками
  </real_object>
</document>
