<?xml version="1.0" encoding="windows-1251"?>
<document>
  <ID>
    14580
  </ID>
  <link>
    http://www.livelib.ru/review/53612
  </link>
  <date>
    2010-03-23T07:50:13Z
  </date>
  <query>
    Бернард Вербер
  </query>
  <text>
    Alyssa прочитала книгу «Наши друзья Человеки» . Автор:
Бернард Вербер На самом деле если бы не одноименный спектакль,
который я недавно посмотрела, эту книгу я бы навряд ли стала
читать... Что можно сказать, этакое массовое, легкое произведение,
которое я прочитала за пару дней между делом. Есть какие-то
отдельные идеи и мысли, которые заставляют задуматься о некоторых
вещах под новым углом, но повторяюсь, лишь отдельные. В целом же
как-то бледновато, особенно вызывает отторжение примитивность и
невежественность Саманты, вообще своеобразное впечатление
складывается о женщине, исходя из данного литературного персонажа.
Да, местами трогательно, местами забавно...но перечитывать буду
навряд ли и другие книги данного автора тоже читать не тянет.
современная литература утопия франция Нейтральная оценка
  </text>
  <score-2>
    2
  </score-2>
  <score-3>
    2
  </score-3>
  <score-5>
    3
  </score-5>
  <type main="+">
    B
  </type>
  <real_object>
    Наши друзья человеки
  </real_object>
</document>
