<?xml version="1.0" encoding="windows-1251"?>
<document>
  <ID>
    1173
  </ID>
  <link>
    http://gfkorob.ya.ru/replies.xml?item_no=1004
  </link>
  <date>
    2010-09-30T08:19:29Z
  </date>
  <query>
    Olympus SP-800 UZ
  </query>
  <text>
    g fkorob написало отзыв опубликовано на Маркете всем
рекомендую :-)) Достоинства: Простое меню, быстро включается. С
помощью 30-ти кратного зума легко находить нужный ракурс для съемки
&quot;не вставая с места&quot;. Купил и пользуйся. Один из самых
дешевых аппаратов с такими характеристиками. На максимальном
увеличении фокусируется достаточно быстро (даже, как мне показалось
при выборе, быстрее Panasonic FZ38 и Nikon P100), размеры и вес и
наличие встренной памяти 2GB делают этот аппарат выгоднее
конкурентов Недостатки: Нет ручных нстроек выдержки и дифрагмы.
Комментарий: Если надо просто снимать без заморочек - Olympes
SP-800 UZ отличный выбор. Если же заморачиваетесь на выборе
настроек - то присмотрите что-то другое (зеркалочку с объективами).
Здесь же - взял в руки и снимай.
  </text>
  <score-2>
    2
  </score-2>
  <score-3>
    2
  </score-3>
  <score-5>
    4
  </score-5>
  <type main="+">
    C
  </type>
  <real_object>
    Olympus SP-800 UZ
  </real_object>
  <type main="-">
    C
  </type>
  <real_object>
    Panasonic FZ38
  </real_object>
  <type main="-">
    C
  </type>
  <real_object>
    Nikon P100
  </real_object>
</document>
