<?xml version="1.0" encoding="windows-1251"?>
<document>
  <ID>
    3910
  </ID>
  <link>
    http://atabekovd.ya.ru/replies.xml?item_no=21240
  </link>
  <date>
    2010-07-25T22:01:43Z
  </date>
  <query>
    Inception
  </query>
  <text>
    Вообще непонятен перевод фильма . Да, inception означает в
прямом переводе &quot;начало&quot;. Но по-моему тут игра слов
ception , что означает &quot;восприятие&quot; и приставки in .
Хотя, это лично мое мнение. Может начало означает начало сна. Фильм
на пятерочку, ес-сно. Да, есть некоторые параллели с матрицей (суть
и спецэффекты. Спецэффекты вообще круть, не слишком много и все
уместно), но обыграны чуть иначе. Финал напряженный, непонятно до
конца будет все ок, или не ок. Хотя так и не понятно, это было
пробуждение от 4 уровней сна и остался ли он в первом или волчок
таки перестал крутиться... И почему в других уровнях тогда он
падал. Непонятно. Мысль, конечно была, что с самого начала это все
сон, но хз.
  </text>
  <score-2>
    2
  </score-2>
  <score-3>
    3
  </score-3>
  <score-5>
    5
  </score-5>
  <type main="+">
    F
  </type>
  <real_object>
    Inception
  </real_object>
</document>
