<?xml version="1.0" encoding="windows-1251"?>
<document>
  <ID>
    621
  </ID>
  <link>
    http://vodolazs.livejournal.com/14276.html
  </link>
  <date>
    2010-08-10T18:27:34Z
  </date>
  <query>
    Nikon D3000 Kit
  </query>
  <text>
    Куплен Nikon D3000 kit 18-105 VR . Не красиво уже стало
каждый раз у друзей просить зеркалку когда куда то еду. А мыльницей
не могу фотографировать из-за их тормознутости и реакции на
спусковую кнопку. Изначально планировалась покупка D90 с этим же
объективом, но оценив все за и против, прикинув, что лишние 4000
грн совсем не лишние. Решил взять Д3000. Протестировать в
нормальных условиях еще не успел. Только собрал прикрутил ремень и
сделал пару фоток. Из недостатков вижу только один - маленькая
тушка, даже по сравнению с Д50 в руке лежит не так удобно, не
говоря уже о Д90. Но думаю это дело привычки. Осталось прикупить
карточки и сумку. Сумка скорее всего Lowepro, модель пока
определяется. Наверно относительно большая, как для одного
объектива, Nova 160 AW. Но из опыта пользования сумкой к Д50, там
не хватало места под ключи, телефон и кошелек, что совсем не
радовало во время прогулки по набережной на море.
  </text>
  <score-2>
    2
  </score-2>
  <score-3>
    3
  </score-3>
  <score-5>
    4
  </score-5>
  <type main="+">
    C
  </type>
  <real_object>
    Nikon D3000 kit 18-105 VR
  </real_object>
</document>
